glam/__init__.py
glam/_lib.py
the_glam-1.0.0.dist-info/METADATA
the_glam-1.0.0.dist-info/WHEEL
the_glam-1.0.0.dist-info/top_level.txt
the_glam-1.0.0.dist-info/RECORD
