Metadata-Version: 2.1
Name: the-glam
Version: 1.0.0
Summary: The Glycopeptide Analysis Module
Requires-Python: >=3.12
Requires-Dist: glycowork>=1.4.0
Requires-Dist: pyteomics>=4.7.5
